biblio_py-0.7.4.data/scripts/bibadmin.py
biblio_py-0.7.4.data/scripts/bibextract.py
biblio_py-0.7.4.data/scripts/bibmanage.py
biblio_py-0.7.4.data/scripts/get_papers.py
biblio_py-0.7.4.data/scripts/test_sqlite.py
query_ads/__init__.py
query_ads/query_ads.py
yapbib/__init__.py
yapbib/adsparse.py
yapbib/bibdb.py
yapbib/bibitem.py
yapbib/biblist.py
yapbib/bibparse.py
yapbib/helper.py
yapbib/latex.py
yapbib/latex_equivalents.py
yapbib/version.py
biblio_py-0.7.4.dist-info/METADATA
biblio_py-0.7.4.dist-info/WHEEL
biblio_py-0.7.4.dist-info/top_level.txt
biblio_py-0.7.4.dist-info/RECORD
