Metadata-Version: 2.1
Name: biblio-py
Version: 0.7.4
Summary: Package to manage bibliography files
Home-page: https://github.com/fiolj/biblio-py
Author: Juan Fiol
Author-email: juanfiol@gmail.com
License: GPLv2
Keywords: bibliography,bibtex,converter,html,xml,latex,parser
Platform: UNKNOWN
